[
  {
    "latitude": 6.315299, 
    "longitude": 27.154349
  }, 
  {
    "latitude": -13.239945, 
    "longitude": -57.980583
  }, 
  {
    "latitude": 20.036057, 
    "longitude": -57.980583
  }, 
  {
    "latitude": -51.618017, 
    "longitude": -59.008979
  }, 
  {
    "latitude": -65.946472, 
    "longitude": -62.878749
  }, 
  {
    "latitude": 8.754795, 
    "longitude": -80.116814
  }, 
  {
    "latitude": -23.885838, 
    "longitude": 44.771207
  }, 
  {
    "latitude": -74.402163, 
    "longitude": 126.816019
  }, 
  {
    "latitude": 78.903929, 
    "longitude": 381.517221
  }, 
  {
    "latitude": -1.406109, 
    "longitude": 121.187264
  }
]